badFormatter/__init__.py
badFormatter/forms.py
badFormatter-1.3.0.dist-info/LICENSE
badFormatter-1.3.0.dist-info/METADATA
badFormatter-1.3.0.dist-info/WHEEL
badFormatter-1.3.0.dist-info/top_level.txt
badFormatter-1.3.0.dist-info/RECORD
