Metadata-Version: 2.1
Name: badFormatter
Version: 1.3.0
Summary: This is a package to format your code into hell. Designed for people who like python and hate '}', '{' and ';'
Home-page: https://github.com/johnmontgomery2003/badFormatter
Author: John Montgomery
Author-email: john@johnmontgomery.tech
License: UNKNOWN
Platform: UNKNOWN
Classifier: Programming Language :: Python :: 3
Classifier: License :: OSI Approved :: MIT License
Classifier: Operating System :: OS Independent
Requires-Python: >=3.6
